[
  {
    "id": "vigil-85feda",
    "title": "defaultToolRegistry() hardcoded tool set",
    "priority": "P2",
    "status": "pending",
    "tags": [
      "tech-debt"
    ],
    "origin": {
      "type": "code_scan",
      "ref": ""
    },
    "depends_on": null,
    "notes": "Needs Agent identity + per-task Contract tool_scopes",
    "created_at": "2026-05-14T11:33:48.4293422+08:00",
    "history": []
  },
  {
    "id": "vigil-8fda37",
    "title": "dispatcher hardcoded AutonomyLevelLow",
    "priority": "P2",
    "status": "pending",
    "tags": [
      "tech-debt"
    ],
    "origin": {
      "type": "code_scan",
      "ref": ""
    },
    "depends_on": null,
    "notes": "Needs competence profile + autonomy rule engine",
    "created_at": "2026-05-14T11:33:48.8492071+08:00",
    "history": []
  },
  {
    "id": "vigil-bda908",
    "title": "multi-turn loop cap=10 termination",
    "priority": "P2",
    "status": "pending",
    "tags": [
      "tech-debt"
    ],
    "origin": {
      "type": "code_scan",
      "ref": ""
    },
    "depends_on": null,
    "notes": "Needs Agent stop signal (__done tool)",
    "created_at": "2026-05-14T11:33:49.307745+08:00",
    "history": []
  },
  {
    "id": "vigil-6e8834",
    "title": "Permission scopes never checked",
    "priority": "P2",
    "status": "pending",
    "tags": [
      "tech-debt"
    ],
    "origin": {
      "type": "code_scan",
      "ref": ""
    },
    "depends_on": null,
    "notes": "Needs Permission Ladder infrastructure",
    "created_at": "2026-05-14T11:33:49.7464986+08:00",
    "history": []
  },
  {
    "id": "vigil-aa60a3",
    "title": "syscall tools are empty shells",
    "priority": "P2",
    "status": "pending",
    "tags": [
      "tech-debt"
    ],
    "origin": {
      "type": "code_scan",
      "ref": ""
    },
    "depends_on": null,
    "notes": "Needs scheduler integration interface",
    "created_at": "2026-05-14T11:33:50.193684+08:00",
    "history": []
  },
  {
    "id": "vigil-2655b5",
    "title": "Set* temporal coupling",
    "priority": "P2",
    "status": "pending",
    "tags": [
      "tech-debt"
    ],
    "origin": {
      "type": "code_scan",
      "ref": ""
    },
    "depends_on": null,
    "notes": "Wait for AgentConfig struct refactor",
    "created_at": "2026-05-14T11:33:50.6212442+08:00",
    "history": []
  },
  {
    "id": "vigil-020f38",
    "title": "circuit breaker=5 hardcoded",
    "priority": "P2",
    "status": "pending",
    "tags": [
      "tech-debt"
    ],
    "origin": {
      "type": "code_scan",
      "ref": ""
    },
    "depends_on": null,
    "notes": "Can be Contract field, low priority",
    "created_at": "2026-05-14T11:33:51.0480199+08:00",
    "history": []
  },
  {
    "id": "vigil-b2f106",
    "title": "dispatcher no audit log",
    "priority": "P2",
    "status": "pending",
    "tags": [
      "tech-debt"
    ],
    "origin": {
      "type": "code_scan",
      "ref": ""
    },
    "depends_on": null,
    "notes": "Needs structured event emitter",
    "created_at": "2026-05-14T11:33:51.4698505+08:00",
    "history": []
  },
  {
    "id": "vigil-1553ac",
    "title": "mock provider silent default",
    "priority": "P2",
    "status": "pending",
    "tags": [
      "tech-debt"
    ],
    "origin": {
      "type": "code_scan",
      "ref": ""
    },
    "depends_on": null,
    "notes": "Reasonable for dev, fix before production",
    "created_at": "2026-05-14T11:33:51.896573+08:00",
    "history": []
  },
  {
    "id": "vigil-4c6383",
    "title": "FileWriteTool path validation weaker than FileReadTool",
    "priority": "P1",
    "status": "completed",
    "tags": [
      "tech-debt",
      "security"
    ],
    "origin": {
      "type": "code_scan",
      "ref": ""
    },
    "depends_on": null,
    "notes": "Security fix, can be done independently",
    "created_at": "2026-05-14T11:33:52.3117147+08:00",
    "started_at": "2026-05-14T11:39:37.3391886+08:00",
    "completed_at": "2026-05-14T11:45:02.5219912+08:00",
    "commit_hash": "ce44079",
    "history": [
      {
        "from": "pending",
        "to": "in_progress",
        "at": "2026-05-14T11:39:37.3391886+08:00"
      },
      {
        "from": "completed",
        "to": "completed",
        "at": "2026-05-14T11:45:02.5219912+08:00"
      }
    ]
  },
  {
    "id": "vigil-c806e2",
    "title": "Judge: generalization scoring (OOD/ID ratio)",
    "priority": "P1",
    "status": "pending",
    "tags": [
      "judge"
    ],
    "origin": {
      "type": "manual",
      "ref": ""
    },
    "depends_on": null,
    "notes": "Agent cannot upgrade on familiar tasks alone. Threshold: \u003e=0.8 upgrade, \u003c0.5 downgrade",
    "created_at": "2026-05-14T11:34:03.6395868+08:00",
    "history": []
  },
  {
    "id": "vigil-ef8c34",
    "title": "Autonomy Transition rule refactor",
    "priority": "P1",
    "status": "pending",
    "tags": [
      "autonomy"
    ],
    "origin": {
      "type": "manual",
      "ref": ""
    },
    "depends_on": null,
    "notes": "Replace consecutive-success with: resource-constrained + OOD + architecture-driven",
    "created_at": "2026-05-14T11:34:04.065694+08:00",
    "history": []
  },
  {
    "id": "vigil-9d684f",
    "title": "Permission Ladder Level 0 whitelist",
    "priority": "P1",
    "status": "completed",
    "tags": [
      "security"
    ],
    "origin": {
      "type": "manual",
      "ref": ""
    },
    "depends_on": null,
    "notes": "Initial command whitelist: ls/cat/grep/wc/git/go build/go test",
    "created_at": "2026-05-14T11:34:04.5149068+08:00",
    "history": []
  },
  {
    "id": "vigil-253bf5",
    "title": "Refactor: split orchestrator",
    "priority": "P1",
    "status": "pending",
    "tags": [
      "refactor"
    ],
    "origin": {
      "type": "manual",
      "ref": ""
    },
    "depends_on": null,
    "notes": "Extract ToolRegistryBuilder + ExecutorFactory, orchestrator only does scheduling loop",
    "created_at": "2026-05-14T11:34:04.9557844+08:00",
    "history": []
  },
  {
    "id": "vigil-69274c",
    "title": "Refactor: AgentConfig struct",
    "priority": "P1",
    "status": "completed",
    "tags": [
      "refactor"
    ],
    "origin": {
      "type": "manual",
      "ref": ""
    },
    "depends_on": null,
    "notes": "Unify provider/tools/skills/compaction into single config, eliminate Set* method chain",
    "created_at": "2026-05-14T11:34:05.3793377+08:00",
    "history": []
  },
  {
    "id": "vigil-1651f6",
    "title": "Subagent context isolation",
    "priority": "P1",
    "status": "pending",
    "tags": [
      "architecture"
    ],
    "origin": {
      "type": "manual",
      "ref": ""
    },
    "depends_on": null,
    "notes": "Parent fresh context dispatch, subagent returns summary only",
    "created_at": "2026-05-14T11:34:05.8034126+08:00",
    "history": []
  },
  {
    "id": "vigil-4f646e",
    "title": "Guarantee Registry",
    "priority": "P1",
    "status": "completed",
    "tags": [
      "architecture"
    ],
    "origin": {
      "type": "manual",
      "ref": ""
    },
    "depends_on": null,
    "notes": "Explicit auditable system guarantees. Sublated from arXiv:2605.12239 Know layer",
    "created_at": "2026-05-14T11:34:06.2229738+08:00",
    "history": []
  },
  {
    "id": "vigil-5e1eab",
    "title": "Quality-Gated Model Escalation",
    "priority": "P1",
    "status": "pending",
    "tags": [
      "architecture"
    ],
    "origin": {
      "type": "manual",
      "ref": ""
    },
    "depends_on": null,
    "notes": "Judge score \u003c threshold -\u003e auto upgrade provider tier. Sublated from arXiv:2605.12239",
    "created_at": "2026-05-14T11:34:06.6477413+08:00",
    "history": []
  },
  {
    "id": "vigil-d8a622",
    "title": "Background Tasks async execution",
    "priority": "P1",
    "status": "pending",
    "tags": [
      "architecture"
    ],
    "origin": {
      "type": "manual",
      "ref": ""
    },
    "depends_on": null,
    "notes": "Slow operations go background, Agent continues thinking",
    "created_at": "2026-05-14T11:34:07.0688035+08:00",
    "history": []
  },
  {
    "id": "vigil-8b8482",
    "title": "Feature progressive unlock (BashTool/Evolution/Permissions)",
    "priority": "P2",
    "status": "pending",
    "tags": [
      "autonomy"
    ],
    "origin": {
      "type": "manual",
      "ref": ""
    },
    "depends_on": null,
    "notes": "30 tasks + accuracy\u003e=90% + generalization\u003e=0.8 + reliability\u003e=95% + zero violations",
    "created_at": "2026-05-14T11:34:17.3231788+08:00",
    "history": []
  },
  {
    "id": "vigil-a2abbc",
    "title": "Unified Capability registration interface",
    "priority": "P2",
    "status": "pending",
    "tags": [
      "refactor"
    ],
    "origin": {
      "type": "manual",
      "ref": ""
    },
    "depends_on": null,
    "notes": "Capability interface (tool + prompt injection + config), register in one line",
    "created_at": "2026-05-14T11:34:17.7554872+08:00",
    "history": []
  },
  {
    "id": "vigil-233b3b",
    "title": "Provider semantic layering (Execute vs Utility)",
    "priority": "P2",
    "status": "pending",
    "tags": [
      "architecture"
    ],
    "origin": {
      "type": "manual",
      "ref": ""
    },
    "depends_on": null,
    "notes": "Independent quotas and model selection for dialogue vs summarization/judge/embedding",
    "created_at": "2026-05-14T11:34:18.209757+08:00",
    "history": []
  },
  {
    "id": "vigil-fd6153",
    "title": "Multi-Agent collaboration (JSONL mailbox)",
    "priority": "P2",
    "status": "pending",
    "tags": [
      "architecture"
    ],
    "origin": {
      "type": "manual",
      "ref": ""
    },
    "depends_on": null,
    "notes": "JSONL mailbox protocol + auto-claim + worktree integration",
    "created_at": "2026-05-14T11:34:18.642982+08:00",
    "history": []
  },
  {
    "id": "vigil-fdb806",
    "title": "Skills composable metadata",
    "priority": "P2",
    "status": "pending",
    "tags": [
      "architecture"
    ],
    "origin": {
      "type": "manual",
      "ref": ""
    },
    "depends_on": null,
    "notes": "input_type/output_type/composable_with in SKILL.md frontmatter. Sublated from arXiv:2605.12239",
    "created_at": "2026-05-14T11:34:19.072044+08:00",
    "history": []
  },
  {
    "id": "vigil-1054a4",
    "title": "CodingAgent spec: requirements.md + design.md",
    "priority": "P1",
    "status": "completed",
    "tags": [
      "coding-agent"
    ],
    "origin": {
      "type": "manual",
      "ref": ""
    },
    "depends_on": null,
    "notes": "Based on first-principles.md, implement 4-Phase tool call ordering + output format Contract",
    "created_at": "2026-05-14T11:34:19.4945461+08:00",
    "started_at": "2026-05-14T11:39:37.7594392+08:00",
    "completed_at": "2026-05-14T11:45:03.1972469+08:00",
    "commit_hash": "b7d795f",
    "history": [
      {
        "from": "pending",
        "to": "in_progress",
        "at": "2026-05-14T11:39:37.7594392+08:00"
      },
      {
        "from": "in_progress",
        "to": "completed",
        "at": "2026-05-14T11:45:03.1972469+08:00"
      }
    ]
  },
  {
    "id": "vigil-1384ea",
    "title": "Research: Symbolic Equivalence Partitioning (arXiv:2604.06485)",
    "priority": "P2",
    "status": "completed",
    "tags": [
      "research"
    ],
    "origin": {
      "type": "",
      "ref": ""
    },
    "depends_on": null,
    "notes": "CodingAgent P2: equivalence classes for code selection. +7.2% at N=10",
    "created_at": "2026-05-14T11:53:26.7092462+08:00",
    "completed_at": "2026-05-14T12:10:27.2399342+08:00",
    "history": [
      {
        "from": "pending",
        "to": "completed",
        "at": "2026-05-14T12:10:27.2399342+08:00"
      }
    ]
  },
  {
    "id": "vigil-71ce28",
    "title": "Research: Variational Posterior Guidance (arXiv:2605.11019)",
    "priority": "P2",
    "status": "completed",
    "tags": [
      "research"
    ],
    "origin": {
      "type": "",
      "ref": ""
    },
    "depends_on": null,
    "notes": "Compression = finding equivalent short paths. Maps to three-layer compaction",
    "created_at": "2026-05-14T11:53:34.0509617+08:00",
    "completed_at": "2026-05-14T12:10:27.6794965+08:00",
    "history": [
      {
        "from": "pending",
        "to": "completed",
        "at": "2026-05-14T12:10:27.6794965+08:00"
      }
    ]
  },
  {
    "id": "vigil-96f52f",
    "title": "Research: Token-Level Hallucination Detection 0.6B (arXiv:2605.12384)",
    "priority": "P2",
    "status": "completed",
    "tags": [
      "research"
    ],
    "origin": {
      "type": "",
      "ref": ""
    },
    "depends_on": null,
    "notes": "Lightweight judge surpasses QwQ-32B. Maps to Judge drafter/verifier pattern",
    "created_at": "2026-05-14T11:53:34.6053212+08:00",
    "completed_at": "2026-05-14T12:10:28.1199978+08:00",
    "history": [
      {
        "from": "pending",
        "to": "completed",
        "at": "2026-05-14T12:10:28.1199978+08:00"
      }
    ]
  },
  {
    "id": "vigil-e94383",
    "title": "Judge must use independent short context (Context Rot fix)",
    "priority": "P0",
    "status": "pending",
    "tags": [
      "security",
      "judge"
    ],
    "origin": {
      "type": "",
      "ref": ""
    },
    "depends_on": null,
    "notes": "arXiv:2605.12366: 800K token后漏检率2x-30x. Judge只看final artifacts+task spec, 不看完整transcript.",
    "created_at": "2026-05-14T11:58:55.1653083+08:00",
    "history": []
  },
  {
    "id": "vigil-5a10ec",
    "title": "CodingAgent: multi-candidate generation + differential testing",
    "priority": "P1",
    "status": "pending",
    "tags": [
      "coding-agent",
      "research"
    ],
    "origin": {
      "type": "",
      "ref": ""
    },
    "depends_on": null,
    "notes": "arXiv:2604.06485 SEP: generate N\u003e=3 candidates, run same inputs, select dominant equivalence class. Replaces single-shot + verify.",
    "created_at": "2026-05-14T12:10:19.6130531+08:00",
    "history": []
  },
  {
    "id": "vigil-2b4048",
    "title": "ContextBundle: task-aware compression scoring",
    "priority": "P2",
    "status": "pending",
    "tags": [
      "contextpack",
      "research"
    ],
    "origin": {
      "type": "",
      "ref": ""
    },
    "depends_on": null,
    "notes": "arXiv:2605.11019 VPG-EA: score context chunks by task relevance before compression. Not simple truncation.",
    "created_at": "2026-05-14T12:10:20.1202144+08:00",
    "history": []
  },
  {
    "id": "vigil-15c221",
    "title": "Judge: lightweight first-pass + escalation gate",
    "priority": "P1",
    "status": "pending",
    "tags": [
      "judge",
      "research"
    ],
    "origin": {
      "type": "",
      "ref": ""
    },
    "depends_on": null,
    "notes": "arXiv:2605.12384 TokenHD: 0.6B beats QwQ-32B at hallucination detection. Cheap judge first, expensive only on demand.",
    "created_at": "2026-05-14T12:10:20.5514906+08:00",
    "history": []
  }
]